vektara/__init__.py
vektara/__main__.py
vektara/data_types.py
vektara/gui.py
vektara-0.0.6.dist-info/LICENSE
vektara-0.0.6.dist-info/METADATA
vektara-0.0.6.dist-info/WHEEL
vektara-0.0.6.dist-info/entry_points.txt
vektara-0.0.6.dist-info/top_level.txt
vektara-0.0.6.dist-info/RECORD
