Metadata-Version: 2.1
Name: vektara
Version: 0.0.6
Summary: An UNofficial Python SDK and CLI for Vectara
Author-email: Forrest Sheng Bao <forrest@vectara.com>
License: GNU GENERAL PUBLIC LICENSE
Project-URL: homepage, https://github.com/forrestbao/vektara
Requires-Python: >=3.10
License-File: LICENSE
